zergmacroplot/__init__.py
zergmacroplot/app.py
zergmacroplot/data/__init__.py
zergmacroplot/data/replay.py
zergmacroplot/static/images/allin_official.png
zergmacroplot/static/styles/main.css
zergmacroplot/storage/__init__.py
zergmacroplot/storage/database.py
zergmacroplot/storage/firebasedatabase.py
zergmacroplot/storage/inmemorydatabase.py
zergmacroplot/storage/util.py
zergmacroplot/templates/analysis.html.j2
zergmacroplot/templates/index.html.j2
zergmacroplot-0.0.16.dist-info/METADATA
zergmacroplot-0.0.16.dist-info/RECORD
zergmacroplot-0.0.16.dist-info/WHEEL
zergmacroplot-0.0.16.dist-info/top_level.txt
